secuMod/__init__.py
secuMod/main.py
tgbot_sec-0.1.0.dist-info/LICENSE
tgbot_sec-0.1.0.dist-info/METADATA
tgbot_sec-0.1.0.dist-info/WHEEL
tgbot_sec-0.1.0.dist-info/top_level.txt
tgbot_sec-0.1.0.dist-info/RECORD
