Metadata-Version: 2.1
Name: tgbot_sec
Version: 0.1.0
Author-email: jffwxs <kvostrecova0207@mail.ru>
Classifier: Programming Language :: Python :: 3
Classifier: License :: OSI Approved :: MIT License
Classifier: Operating System :: OS Independent
Requires-Python: >=3.10.0
License-File: LICENSE
